flowify/__init__.py
flowify/__main__.py
flowify/drawing.py
flowify-0.1.0.dist-info/entry_points.txt
flowify-0.1.0.dist-info/LICENSE
flowify-0.1.0.dist-info/WHEEL
flowify-0.1.0.dist-info/METADATA
flowify-0.1.0.dist-info/RECORD
