Metadata-Version: 2.1
Name: flowify
Version: 0.1.0
Summary: Interrogate a font file
License: MIT
Author: Simon Cozens
Author-email: simon@simon-cozens.org
Requires-Python: >=3.5,<4
Classifier: License :: OSI Approved :: MIT License
Classifier: Programming Language :: Python :: 3
Classifier: Programming Language :: Python :: 3.10
Classifier: Programming Language :: Python :: 3.5
Classifier: Programming Language :: Python :: 3.6
Classifier: Programming Language :: Python :: 3.7
Classifier: Programming Language :: Python :: 3.8
Classifier: Programming Language :: Python :: 3.9
Requires-Dist: fontfeatures
Requires-Dist: inflect
Requires-Dist: numpy
Requires-Dist: ufo2ft
Requires-Dist: ufoLib2
